arcmg/__init__.py
arcmg/config.py
arcmg/data.py
arcmg/network.py
arcmg/plot.py
arcmg/system.py
arcmg/training.py
arcmg/utils.py
arcmg-0.0.2.dist-info/LICENSE
arcmg-0.0.2.dist-info/METADATA
arcmg-0.0.2.dist-info/WHEEL
arcmg-0.0.2.dist-info/top_level.txt
arcmg-0.0.2.dist-info/RECORD
