Metadata-Version: 2.1
Name: arcmg
Version: 0.0.2
Summary: arcmg: Attracting Regions Classifier by Morse Graph
Home-page: https://github.com/Ewerton-Vieira/arcmg.git
Author: Brittany Gelb, Ewerton Rocha Vieira
License-File: LICENSE
Requires-Dist: numpy
Requires-Dist: torch
Requires-Dist: igraph
Requires-Dist: plotly
Requires-Dist: pandas
Requires-Dist: seaborn
Requires-Dist: matplotlib
Requires-Dist: pyyaml
